sage_seo/__init__.py
sage_seo/admin/__init__.py
sage_seo/admin/actions/__init__.py
sage_seo/admin/actions/robot.py
sage_seo/admin/meta_info.py
sage_seo/admin/robot.py
sage_seo/admin/script_tag.py
sage_seo/admin/slug_swap.py
sage_seo/admin/url_redirect.py
sage_seo/apps.py
sage_seo/context_processor.py
sage_seo/forms/__init__.py
sage_seo/forms/seo.py
sage_seo/funcs.py
sage_seo/helpers/__init__.py
sage_seo/helpers/choices.py
sage_seo/helpers/enums.py
sage_seo/locale/ar/LC_MESSAGES/django.po
sage_seo/locale/en/LC_MESSAGES/django.po
sage_seo/locale/fa/LC_MESSAGES/django.mo
sage_seo/locale/fa/LC_MESSAGES/django.po
sage_seo/middleware/__init__.py
sage_seo/middleware/slug_swap.py
sage_seo/middleware/url_redirect.py
sage_seo/migrations/0001_initial.py
sage_seo/migrations/__init__.py
sage_seo/models/__init__.py
sage_seo/models/meta_info.py
sage_seo/models/mixins/__init__.py
sage_seo/models/mixins/seo.py
sage_seo/models/robot.py
sage_seo/models/script_tag.py
sage_seo/models/slug_swap.py
sage_seo/models/url_redirect.py
sage_seo/models/validators.py
sage_seo/schemas/__init__.py
sage_seo/schemas/blog.py
sage_seo/schemas/product.py
sage_seo/schemas/static.py
sage_seo/templates/index.html
sage_seo/templatetags/__init__.py
sage_seo/templatetags/seo.py
sage_seo/urls.py
sage_seo/views/__init__.py
sage_seo/views/robot.py
django_sage_seo-0.3.15.dist-info/LICENSE
django_sage_seo-0.3.15.dist-info/METADATA
django_sage_seo-0.3.15.dist-info/WHEEL
django_sage_seo-0.3.15.dist-info/RECORD
