Metadata-Version: 2.1
Name: django-sage-seo
Version: 0.3.15
Summary: SEO tools for Django
License: MIT
Author: Sepehr Akbarzadeh
Author-email: sepehr@sageteam.org
Requires-Python: >=3.8,<4.0
Classifier: Environment :: Web Environment
Classifier: Framework :: Django
Classifier: Framework :: Django :: 4.2
Classifier: Framework :: Django :: 5.0
Classifier: Framework :: Django :: 5.1
Classifier: License :: OSI Approved :: MIT License
Classifier: Operating System :: OS Independent
Classifier: Programming Language :: Python
Classifier: Programming Language :: Python :: 3
Classifier: Programming Language :: Python :: 3.8
Classifier: Programming Language :: Python :: 3.9
Classifier: Programming Language :: Python :: 3.10
Classifier: Programming Language :: Python :: 3.11
Classifier: Programming Language :: Python :: 3.12
Classifier: Programming Language :: Python :: 3 :: Only
Provides-Extra: json-forms
Requires-Dist: django (>=4.2,<5.0) ; python_version >= "3.8" and python_version < "3.10"
Requires-Dist: django (>=4.2,<5.3) ; python_version >= "3.10"
Requires-Dist: django-jsonforms (>=1.0,<3.0)
Requires-Dist: django-sage-tools (>=0.3.5,<0.4.0)
Project-URL: Documentation, https://django-sage-seo.readthedocs.io
Project-URL: Issues, https://github.com/sageteamorg/django-sage-seo/issues
Project-URL: Source Code, https://github.com/sageteamorg/django-sage-seo
